{"version": 0.6, "generator": "Overpass API 0.7.62.8 e802775f", "osm3s": {"timestamp_osm_base": "2025-11-03T08:17:05Z", "copyright": "The data included in this document is from www.openstreetmap.org. The data is made available under ODbL."}, "elements": [{"type": "node", "id": 8851768671, "lat": 44.069952, "lon": -102.4453241}, {"type": "node", "id": 8851768682, "lat": 44.0704284, "lon": -102.4456011}, {"type": "node", "id": 8851768683, "lat": 44.0699513, "lon": -102.4455988}, {"type": "node", "id": 8851768684, "lat": 44.0699524, "lon": -102.4451375}, {"type": "node", "id": 8851768685, "lat": 44.0704295, "lon": -102.4451397}, {"type": "way", "id": 956453700, "nodes": [8851768682, 8851768683, 8851768671, 8851768684, 8851768685, 8851768682], "tags": {"leisure": "park", "source": "Esri"}}]}