{"version": 0.6, "generator": "Overpass API 0.7.62.8 e802775f", "osm3s": {"timestamp_osm_base": "2025-12-06T04:19:16Z", "copyright": "The data included in this document is from www.openstreetmap.org. The data is made available under ODbL."}, "elements": [{"type": "node", "id": 10766806639, "lat": 45.703325, "lon": -111.0311295, "tags": {"name": "Resonon", "office": "yes"}}, {"type": "node", "id": 10766806649, "lat": 45.7044916, "lon": -111.0219229, "tags": {"name": "Natural Resources Conservation", "office": "government"}}]}