{"version": 0.6, "generator": "Overpass API 0.7.62.8 e802775f", "osm3s": {"timestamp_osm_base": "2025-11-03T05:34:29Z", "copyright": "The data included in this document is from www.openstreetmap.org. The data is made available under ODbL."}, "elements": [{"type": "node", "id": 5462683969, "lat": 40.6603678, "lon": -80.5993532}, {"type": "node", "id": 5462683970, "lat": 40.660324, "lon": -80.5991244}, {"type": "node", "id": 5462683971, "lat": 40.6602001, "lon": -80.599166}, {"type": "node", "id": 5462683972, "lat": 40.6602451, "lon": -80.5993932}, {"type": "way", "id": 567543966, "nodes": [5462683969, 5462683970, 5462683971, 5462683972, 5462683969], "tags": {"fee": "yes", "fixme": "Check tagging; used proposed sport=batting_cage along with sport=basketball and sport=softball (fast/slow pitch options are available for both sports)", "leisure": "pitch", "operator": "Hidden Oaks Golf", "sport": "batting_cage;basketball;softball", "surface": "concrete"}}]}